plotair/__init__.py
plotair/config.toml
plotair/main.py
plotair-0.2.1.dist-info/METADATA
plotair-0.2.1.dist-info/WHEEL
plotair-0.2.1.dist-info/entry_points.txt
plotair-0.2.1.dist-info/licenses/LICENSE
plotair-0.2.1.dist-info/RECORD
