Metadata-Version: 2.4
Name: plotair
Version: 0.2.1
Summary: Generate CO₂, humidity and temperature plots from VisiblAir sensor CSV files.
Project-URL: Repository, https://github.com/monsieurlinux/plotair
Author-email: Monsieur Linux <info@mlinux.ca>
License-Expression: MIT
License-File: LICENSE
Keywords: cli,data-analysis,data-science,iot,monitoring,python,terminal,visualization
Classifier: Operating System :: OS Independent
Classifier: Programming Language :: Python :: 3
Requires-Python: >=3.11
Requires-Dist: pandas<3.0.0,>=2.0.0
Requires-Dist: seaborn<1.0.0,>=0.13.2
